donatellopyzza/__init__.py
donatellopyzza/assessor.py
donatellopyzza/envBuilder.py
donatellopyzza/game.py
donatellopyzza/main_assessor.py
donatellopyzza/main_generate.py
donatellopyzza/mazeGenerator.py
donatellopyzza/turtleAgent.py
donatellopyzza/data/environments/assessment_maze.png
donatellopyzza/data/environments/assessment_maze.txt
donatellopyzza/data/environments/hard_maze.txt
donatellopyzza/data/environments/maze.txt
donatellopyzza/data/environments/test.png
donatellopyzza/data/environments/test.txt
donatellopyzza/data/images/pizza.png
donatellopyzza/data/images/turtle.png
donatellopyzza/data/images/turtle_small.png
donatellopyzza/grid/__init__.py
donatellopyzza/grid/agent.py
donatellopyzza/grid/careTaker.py
donatellopyzza/grid/constants.py
donatellopyzza/grid/grid.py
donatellopyzza/grid/gui.py
donatellopyzza/grid/map.py
donatellopyzza/grid/mazeParser.py
donatellopyzza/grid/memento.py
donatellopyzza/grid/orientation.py
donatellopyzza/grid/originator.py
donatellopyzza/grid/square.py
donatellopyzza/grid/turn.py
donatellopyzza-1.6.6.dist-info/METADATA
donatellopyzza-1.6.6.dist-info/WHEEL
donatellopyzza-1.6.6.dist-info/licenses/LICENSE
donatellopyzza-1.6.6.dist-info/RECORD
