Metadata-Version: 2.1
Name: DonatelloPyzza
Version: 1.6.6
Summary: A simple and educational game to learn algorithmic where you can develop the behavior of a turtle to move in a maze.
Project-URL: Homepage, https://github.com/MilowB/Donatello
Project-URL: Bug Tracker, https://github.com/MilowB/Donatello/pulls
Author-email: Mickaël Bettinelli <mickael.bettinelli@univ-smb.fr>
License-File: LICENSE
Classifier: License :: Free for non-commercial use
Classifier: Operating System :: OS Independent
Classifier: Programming Language :: Python :: 3
Requires-Python: >=3.1
Requires-Dist: pygame==2.1.2
Requires-Dist: tqdm
